{
  "parameters": {
    "api-version": "2021-08-01-preview",
    "subscriptionId": "00000000-0000-0000-0000-000000000000",
    "resourceGroupName": "myResourceGroup",
    "registryName": "myRegistry",
    "refreshDelegatedResourceIdentityParameters": {
      "sourceResourceInternalIds": [
        "00000000-0000-0000-0000-000000000001",
        "00000000-0000-0000-0000-000000000002"
      ]
    }
  },
  "responses": {
    "200": {},
    "202": {},
    "400": {},
    "403": {},
    "404": {}
  }
}
